[
  {
    "serial": "8459057223"
  },
  {
    "serial": "9530168922"
  },
  {
    "serial": "9228346483"
  },
  {
    "serial": "9407562066"
  },
  {
    "serial": "0594875080"
  },
  {
    "serial": "7827690038"
  },
  {
    "serial": "0148208549"
  },
  {
    "serial": "0205132178"
  },
  {
    "serial": "3852654114"
  },
  {
    "serial": "1717148769"
  },
  {
    "serial": "2911423610"
  },
  {
    "serial": "6624809577"
  },
  {
    "serial": "0711735308"
  },
  {
    "serial": "3222521738"
  },
  {
    "serial": "5291524626"
  },
  {
    "serial": "6523607445"
  },
  {
    "serial": "5377063838"
  },
  {
    "serial": "6832670183"
  },
  {
    "serial": "3484575737"
  },
  {
    "serial": "8661131840"
  },
  {
    "serial": "7439007266"
  },
  {
    "serial": "8101195348"
  },
  {
    "serial": "6522744223"
  },
  {
    "serial": "7588253216"
  },
  {
    "serial": "0530936525"
  },
  {
    "serial": "0086919537"
  },
  {
    "serial": "7160220971"
  },
  {
    "serial": "0153193255"
  },
  {
    "serial": "1552019091"
  },
  {
    "serial": "9029898385"
  },
  {
    "serial": "4310577582"
  },
  {
    "serial": "0142110402"
  },
  {
    "serial": "2761023445"
  },
  {
    "serial": "1155727181"
  },
  {
    "serial": "8435024578"
  },
  {
    "serial": "3898849355"
  },
  {
    "serial": "0722095429"
  },
  {
    "serial": "7803261283"
  },
  {
    "serial": "4712567371"
  },
  {
    "serial": "2746744073"
  },
  {
    "serial": "0506473586"
  },
  {
    "serial": "1091659985"
  },
  {
    "serial": "6357392619"
  },
  {
    "serial": "6827838209"
  },
  {
    "serial": "4667843454"
  },
  {
    "serial": "6340953360"
  },
  {
    "serial": "9562395047"
  },
  {
    "serial": "6329643115"
  },
  {
    "serial": "1742087651"
  },
  {
    "serial": "6829735544"
  },
  {
    "serial": "0469270813"
  },
  {
    "serial": "3769797857"
  },
  {
    "serial": "1004258792"
  },
  {
    "serial": "7238750405"
  },
  {
    "serial": "2478315597"
  },
  {
    "serial": "8135368283"
  },
  {
    "serial": "1147177560"
  },
  {
    "serial": "8372286495"
  },
  {
    "serial": "8318001560"
  },
  {
    "serial": "3642989184"
  },
  {
    "serial": "1964831018"
  },
  {
    "serial": "0608055919"
  },
  {
    "serial": "4552917488"
  },
  {
    "serial": "1029169081"
  },
  {
    "serial": "7192373970"
  },
  {
    "serial": "9386824529"
  },
  {
    "serial": "1171298662"
  },
  {
    "serial": "6235589691"
  },
  {
    "serial": "7083494133"
  },
  {
    "serial": "6561519544"
  },
  {
    "serial": "1885031706"
  },
  {
    "serial": "7080939346"
  },
  {
    "serial": "5355830513"
  },
  {
    "serial": "7959637336"
  },
  {
    "serial": "7210487851"
  },
  {
    "serial": "7962157835"
  },
  {
    "serial": "7271999232"
  },
  {
    "serial": "4753037797"
  },
  {
    "serial": "5934224568"
  },
  {
    "serial": "7637016382"
  },
  {
    "serial": "7784015955"
  },
  {
    "serial": "4147160362"
  },
  {
    "serial": "9391565190"
  },
  {
    "serial": "8965220729"
  },
  {
    "serial": "7171609352"
  },
  {
    "serial": "3813235532"
  },
  {
    "serial": "7047001685"
  },
  {
    "serial": "7496375200"
  },
  {
    "serial": "3881804912"
  },
  {
    "serial": "6819740686"
  },
  {
    "serial": "9108228819"
  },
  {
    "serial": "3557281841"
  },
  {
    "serial": "0106806441"
  },
  {
    "serial": "6790488677"
  },
  {
    "serial": "5238976996"
  },
  {
    "serial": "5564988813"
  },
  {
    "serial": "5206049123"
  },
  {
    "serial": "3611923388"
  },
  {
    "serial": "3118115801"
  },
  {
    "serial": "5152248224"
  },
  {
    "serial": "7364138300"
  },
  {
    "serial": "7058439089"
  },
  {
    "serial": "1514352804"
  },
  {
    "serial": "6559098782"
  },
  {
    "serial": "3371602511"
  },
  {
    "serial": "3415837289"
  },
  {
    "serial": "5515975745"
  },
  {
    "serial": "5185654216"
  },
  {
    "serial": "1835956770"
  },
  {
    "serial": "6315965332"
  },
  {
    "serial": "0761821917"
  },
  {
    "serial": "0746301936"
  },
  {
    "serial": "1768994533"
  },
  {
    "serial": "3466578345"
  },
  {
    "serial": "8431785503"
  },
  {
    "serial": "0098603541"
  },
  {
    "serial": "0766216303"
  },
  {
    "serial": "4136516590"
  },
  {
    "serial": "4495251953"
  },
  {
    "serial": "8303984523"
  },
  {
    "serial": "6069210620"
  },
  {
    "serial": "5049178204"
  },
  {
    "serial": "9965458186"
  },
  {
    "serial": "7684503191"
  },
  {
    "serial": "7832326941"
  },
  {
    "serial": "8076867897"
  },
  {
    "serial": "2947920167"
  },
  {
    "serial": "1993555000"
  },
  {
    "serial": "9665354891"
  },
  {
    "serial": "5197603904"
  },
  {
    "serial": "7695451174"
  },
  {
    "serial": "4231084213"
  },
  {
    "serial": "8830747088"
  },
  {
    "serial": "1321234567"
  },
  {
    "serial": "0516859873"
  },
  {
    "serial": "6264861417"
  },
  {
    "serial": "4162470316"
  },
  {
    "serial": "7349949839"
  },
  {
    "serial": "9554370107"
  },
  {
    "serial": "7635614915"
  },
  {
    "serial": "1258355187"
  },
  {
    "serial": "0476249594"
  },
  {
    "serial": "0782605513"
  },
  {
    "serial": "2784032530"
  },
  {
    "serial": "6184317995"
  },
  {
    "serial": "7748223026"
  },
  {
    "serial": "2319502098"
  },
  {
    "serial": "0194595138"
  },
  {
    "serial": "6469744814"
  },
  {
    "serial": "2541955387"
  },
  {
    "serial": "6863528508"
  },
  {
    "serial": "6230839281"
  },
  {
    "serial": "4163333307"
  },
  {
    "serial": "2673114787"
  },
  {
    "serial": "2180407047"
  },
  {
    "serial": "7011439713"
  },
  {
    "serial": "0044862753"
  },
  {
    "serial": "6011126593"
  },
  {
    "serial": "4863213056"
  },
  {
    "serial": "2971735143"
  },
  {
    "serial": "9916778567"
  },
  {
    "serial": "3873781730"
  },
  {
    "serial": "5844245273"
  },
  {
    "serial": "8933812755"
  },
  {
    "serial": "0692116205"
  },
  {
    "serial": "4257618092"
  },
  {
    "serial": "0207717174"
  },
  {
    "serial": "5691009624"
  },
  {
    "serial": "4932731054"
  },
  {
    "serial": "2933500650"
  },
  {
    "serial": "5699660741"
  },
  {
    "serial": "3172591210"
  },
  {
    "serial": "5312054447"
  },
  {
    "serial": "1743461244"
  },
  {
    "serial": "7630340813"
  },
  {
    "serial": "7273914080"
  },
  {
    "serial": "4219921444"
  },
  {
    "serial": "6616791718"
  },
  {
    "serial": "5049397291"
  },
  {
    "serial": "9834797749"
  },
  {
    "serial": "7407439764"
  },
  {
    "serial": "6319470685"
  },
  {
    "serial": "7520138921"
  },
  {
    "serial": "6917571348"
  },
  {
    "serial": "5708476758"
  },
  {
    "serial": "2893394227"
  },
  {
    "serial": "5238075559"
  },
  {
    "serial": "9708743126"
  },
  {
    "serial": "5014182306"
  },
  {
    "serial": "2057427631"
  },
  {
    "serial": "7976826425"
  },
  {
    "serial": "6015875526"
  },
  {
    "serial": "3754434656"
  },
  {
    "serial": "2404480168"
  },
  {
    "serial": "5375470977"
  },
  {
    "serial": "0514251438"
  },
  {
    "serial": "6360339144"
  },
  {
    "serial": "7684540235"
  },
  {
    "serial": "6182530508"
  },
  {
    "serial": "6156323880"
  },
  {
    "serial": "4394028908"
  },
  {
    "serial": "7690289470"
  },
  {
    "serial": "4044583708"
  },
  {
    "serial": "9455382714"
  },
  {
    "serial": "1486796343"
  },
  {
    "serial": "1273709814"
  },
  {
    "serial": "5361270480"
  },
  {
    "serial": "8711830540"
  },
  {
    "serial": "5936453686"
  },
  {
    "serial": "9987330819"
  },
  {
    "serial": "5138053896"
  },
  {
    "serial": "2489630505"
  },
  {
    "serial": "3652573985"
  },
  {
    "serial": "9848530946"
  },
  {
    "serial": "2599234321"
  },
  {
    "serial": "3798717975"
  },
  {
    "serial": "5510582843"
  },
  {
    "serial": "7229687756"
  },
  {
    "serial": "5795184059"
  },
  {
    "serial": "5850610121"
  },
  {
    "serial": "0401081591"
  },
  {
    "serial": "7148601318"
  },
  {
    "serial": "6327426158"
  },
  {
    "serial": "9459364775"
  },
  {
    "serial": "5268370334"
  },
  {
    "serial": "8569976460"
  },
  {
    "serial": "3568804235"
  },
  {
    "serial": "1060737663"
  },
  {
    "serial": "3679269740"
  },
  {
    "serial": "7665462961"
  },
  {
    "serial": "8070312726"
  },
  {
    "serial": "5550199920"
  },
  {
    "serial": "7579484911"
  },
  {
    "serial": "3644580528"
  },
  {
    "serial": "9145665577"
  },
  {
    "serial": "2169840515"
  },
  {
    "serial": "9183651604"
  },
  {
    "serial": "7351929570"
  },
  {
    "serial": "0144151032"
  },
  {
    "serial": "5186430939"
  },
  {
    "serial": "2902111356"
  },
  {
    "serial": "4239992995"
  },
  {
    "serial": "4664271576"
  },
  {
    "serial": "5831361125"
  },
  {
    "serial": "6504117604"
  },
  {
    "serial": "2116976925"
  },
  {
    "serial": "4976182149"
  },
  {
    "serial": "8617322998"
  },
  {
    "serial": "7775800118"
  },
  {
    "serial": "7106276137"
  },
  {
    "serial": "7854418972"
  },
  {
    "serial": "5205119646"
  },
  {
    "serial": "5208245810"
  },
  {
    "serial": "7361429207"
  },
  {
    "serial": "5500573950"
  },
  {
    "serial": "9751631780"
  },
  {
    "serial": "0810181362"
  },
  {
    "serial": "8884680789"
  },
  {
    "serial": "4005984762"
  },
  {
    "serial": "2605345087"
  },
  {
    "serial": "7442728148"
  },
  {
    "serial": "7423578702"
  },
  {
    "serial": "6264679488"
  },
  {
    "serial": "7062619387"
  },
  {
    "serial": "4143654756"
  },
  {
    "serial": "5985941391"
  },
  {
    "serial": "9618196084"
  },
  {
    "serial": "4890623715"
  },
  {
    "serial": "9283765049"
  },
  {
    "serial": "1517430896"
  },
  {
    "serial": "8097566981"
  },
  {
    "serial": "0013316294"
  },
  {
    "serial": "3735458683"
  },
  {
    "serial": "6344575128"
  },
  {
    "serial": "9098660922"
  },
  {
    "serial": "7820618515"
  },
  {
    "serial": "9397186546"
  },
  {
    "serial": "2902715768"
  },
  {
    "serial": "8880389849"
  },
  {
    "serial": "4976239303"
  },
  {
    "serial": "9706100956"
  },
  {
    "serial": "5175113710"
  },
  {
    "serial": "7009124038"
  },
  {
    "serial": "9662253369"
  },
  {
    "serial": "9109007162"
  },
  {
    "serial": "2681259459"
  },
  {
    "serial": "0017640186"
  },
  {
    "serial": "7873032218"
  },
  {
    "serial": "1866743261"
  },
  {
    "serial": "2231826252"
  },
  {
    "serial": "6115577030"
  },
  {
    "serial": "9336965893"
  },
  {
    "serial": "9097343769"
  },
  {
    "serial": "2868906195"
  },
  {
    "serial": "9115704315"
  },
  {
    "serial": "2850332301"
  },
  {
    "serial": "7359121618"
  },
  {
    "serial": "0743835910"
  },
  {
    "serial": "4950772774"
  },
  {
    "serial": "0365671783"
  },
  {
    "serial": "2389368198"
  },
  {
    "serial": "0311349294"
  },
  {
    "serial": "3159571565"
  },
  {
    "serial": "1919032977"
  },
  {
    "serial": "4653651473"
  },
  {
    "serial": "3703803928"
  },
  {
    "serial": "1943282259"
  },
  {
    "serial": "6968960416"
  },
  {
    "serial": "9153973061"
  },
  {
    "serial": "8367014050"
  },
  {
    "serial": "0134281765"
  },
  {
    "serial": "5317293792"
  },
  {
    "serial": "2999933407"
  },
  {
    "serial": "2867904431"
  },
  {
    "serial": "5087482492"
  },
  {
    "serial": "0059723379"
  },
  {
    "serial": "2309662084"
  },
  {
    "serial": "4163195474"
  },
  {
    "serial": "5962948286"
  },
  {
    "serial": "6022549197"
  },
  {
    "serial": "0584188130"
  },
  {
    "serial": "6407659751"
  },
  {
    "serial": "6788557558"
  },
  {
    "serial": "7854202210"
  },
  {
    "serial": "6956323635"
  },
  {
    "serial": "3971590736"
  },
  {
    "serial": "3210296996"
  },
  {
    "serial": "8072914453"
  },
  {
    "serial": "7995116642"
  },
  {
    "serial": "1269217566"
  },
  {
    "serial": "0037360278"
  },
  {
    "serial": "2523936173"
  },
  {
    "serial": "5246426034"
  },
  {
    "serial": "3406752174"
  },
  {
    "serial": "3055205607"
  },
  {
    "serial": "2225669023"
  },
  {
    "serial": "0492445853"
  },
  {
    "serial": "7319689449"
  },
  {
    "serial": "3699336719"
  },
  {
    "serial": "5043072932"
  },
  {
    "serial": "5459091715"
  },
  {
    "serial": "9972067830"
  },
  {
    "serial": "6661452224"
  },
  {
    "serial": "7945733975"
  },
  {
    "serial": "2310690702"
  },
  {
    "serial": "1093059127"
  },
  {
    "serial": "5317537990"
  },
  {
    "serial": "5110437133"
  },
  {
    "serial": "6214001890"
  },
  {
    "serial": "2494944545"
  },
  {
    "serial": "4013002706"
  },
  {
    "serial": "8788948795"
  },
  {
    "serial": "4916094016"
  },
  {
    "serial": "9804683473"
  },
  {
    "serial": "3880366939"
  },
  {
    "serial": "2760807053"
  },
  {
    "serial": "6892092039"
  },
  {
    "serial": "6802720380"
  },
  {
    "serial": "3224274492"
  },
  {
    "serial": "1838959680"
  },
  {
    "serial": "2773816638"
  },
  {
    "serial": "7273140256"
  },
  {
    "serial": "9929312065"
  },
  {
    "serial": "1379688433"
  },
  {
    "serial": "3819434311"
  },
  {
    "serial": "2655206072"
  },
  {
    "serial": "4756755148"
  },
  {
    "serial": "0473468031"
  },
  {
    "serial": "3489063325"
  },
  {
    "serial": "8144281121"
  },
  {
    "serial": "2174618427"
  },
  {
    "serial": "5510243834"
  },
  {
    "serial": "4722138270"
  },
  {
    "serial": "3367605304"
  },
  {
    "serial": "8302615417"
  },
  {
    "serial": "0165718230"
  },
  {
    "serial": "5357728707"
  },
  {
    "serial": "5839580932"
  },
  {
    "serial": "6157469880"
  },
  {
    "serial": "4934066111"
  },
  {
    "serial": "0811130392"
  },
  {
    "serial": "4308042318"
  },
  {
    "serial": "9652573131"
  },
  {
    "serial": "1282035029"
  },
  {
    "serial": "9147059076"
  },
  {
    "serial": "6480055562"
  },
  {
    "serial": "3131401568"
  },
  {
    "serial": "8508673376"
  },
  {
    "serial": "4562849390"
  },
  {
    "serial": "0158727628"
  },
  {
    "serial": "8214471834"
  },
  {
    "serial": "8037119784"
  },
  {
    "serial": "6682958282"
  },
  {
    "serial": "8382093378"
  },
  {
    "serial": "8910251852"
  },
  {
    "serial": "9274099028"
  },
  {
    "serial": "2522219167"
  },
  {
    "serial": "4767606488"
  },
  {
    "serial": "6715930126"
  },
  {
    "serial": "4939905800"
  },
  {
    "serial": "8574337807"
  },
  {
    "serial": "8818062468"
  },
  {
    "serial": "4706100429"
  },
  {
    "serial": "2419879321"
  },
  {
    "serial": "1770332417"
  },
  {
    "serial": "0979527926"
  },
  {
    "serial": "3609645399"
  },
  {
    "serial": "8809752176"
  },
  {
    "serial": "5750349853"
  },
  {
    "serial": "0260864616"
  },
  {
    "serial": "6764423593"
  },
  {
    "serial": "6265319092"
  },
  {
    "serial": "0315632737"
  },
  {
    "serial": "5849789903"
  },
  {
    "serial": "1723543284"
  },
  {
    "serial": "2890759711"
  },
  {
    "serial": "2599389992"
  },
  {
    "serial": "2808877670"
  },
  {
    "serial": "6652290880"
  },
  {
    "serial": "0183670140"
  },
  {
    "serial": "8269370931"
  },
  {
    "serial": "5195064133"
  },
  {
    "serial": "2211057290"
  },
  {
    "serial": "9664710937"
  },
  {
    "serial": "1863913842"
  },
  {
    "serial": "5631324109"
  },
  {
    "serial": "4248014682"
  },
  {
    "serial": "2239075381"
  },
  {
    "serial": "4105717245"
  },
  {
    "serial": "2118428396"
  },
  {
    "serial": "4953735687"
  },
  {
    "serial": "3436578433"
  },
  {
    "serial": "6961456065"
  },
  {
    "serial": "5024284019"
  },
  {
    "serial": "5251092036"
  },
  {
    "serial": "5901628270"
  },
  {
    "serial": "7169270753"
  },
  {
    "serial": "2658800335"
  },
  {
    "serial": "8168139114"
  },
  {
    "serial": "7083704382"
  },
  {
    "serial": "3648381634"
  },
  {
    "serial": "4977148669"
  },
  {
    "serial": "8601540357"
  },
  {
    "serial": "0055747562"
  },
  {
    "serial": "9847671915"
  },
  {
    "serial": "2269730293"
  },
  {
    "serial": "7814954009"
  },
  {
    "serial": "7035518377"
  },
  {
    "serial": "2895689723"
  },
  {
    "serial": "3624831107"
  },
  {
    "serial": "7935514377"
  },
  {
    "serial": "3770510968"
  },
  {
    "serial": "4243254291"
  },
  {
    "serial": "5377956049"
  },
  {
    "serial": "8365011280"
  },
  {
    "serial": "8214782826"
  },
  {
    "serial": "8239197141"
  },
  {
    "serial": "4247460373"
  },
  {
    "serial": "4276695550"
  },
  {
    "serial": "3388723540"
  },
  {
    "serial": "9920586535"
  },
  {
    "serial": "4449380833"
  },
  {
    "serial": "6881699869"
  },
  {
    "serial": "9763411056"
  },
  {
    "serial": "1401234677"
  },
  {
    "serial": "9697807775"
  },
  {
    "serial": "0515450377"
  },
  {
    "serial": "5497955681"
  },
  {
    "serial": "1915589798"
  },
  {
    "serial": "8765786424"
  },
  {
    "serial": "3828021695"
  },
  {
    "serial": "2058135902"
  },
  {
    "serial": "1861758728"
  },
  {
    "serial": "5173534750"
  },
  {
    "serial": "9809965669"
  },
  {
    "serial": "9627176291"
  },
  {
    "serial": "2562404166"
  },
  {
    "serial": "3073463451"
  },
  {
    "serial": "9390642354"
  },
  {
    "serial": "5161961221"
  },
  {
    "serial": "1783554452"
  },
  {
    "serial": "3552215281"
  },
  {
    "serial": "2624688210"
  },
  {
    "serial": "0820709913"
  },
  {
    "serial": "8956641115"
  },
  {
    "serial": "5282135218"
  },
  {
    "serial": "0252402094"
  },
  {
    "serial": "8690154672"
  },
  {
    "serial": "0032729121"
  },
  {
    "serial": "4697275891"
  },
  {
    "serial": "2606307318"
  },
  {
    "serial": "8740804920"
  },
  {
    "serial": "8548859274"
  },
  {
    "serial": "3801190053"
  },
  {
    "serial": "4857770467"
  },
  {
    "serial": "9088460549"
  },
  {
    "serial": "3572444879"
  },
  {
    "serial": "8763608372"
  },
  {
    "serial": "8005389641"
  },
  {
    "serial": "7792368206"
  },
  {
    "serial": "1173648443"
  },
  {
    "serial": "8490887612"
  },
  {
    "serial": "4807255056"
  },
  {
    "serial": "3167808504"
  },
  {
    "serial": "8872944635"
  },
  {
    "serial": "2962181497"
  },
  {
    "serial": "8110256552"
  },
  {
    "serial": "6927627247"
  },
  {
    "serial": "8071473659"
  },
  {
    "serial": "3209246374"
  },
  {
    "serial": "6157088573"
  },
  {
    "serial": "3513507651"
  },
  {
    "serial": "1212581662"
  },
  {
    "serial": "9003912145"
  },
  {
    "serial": "9545424054"
  },
  {
    "serial": "3253508448"
  },
  {
    "serial": "2289852598"
  },
  {
    "serial": "4367235043"
  },
  {
    "serial": "6261107301"
  },
  {
    "serial": "6361934877"
  },
  {
    "serial": "4856736790"
  },
  {
    "serial": "9539698127"
  },
  {
    "serial": "9913568144"
  },
  {
    "serial": "4391563907"
  },
  {
    "serial": "3921190249"
  },
  {
    "serial": "3708863901"
  },
  {
    "serial": "2269064529"
  },
  {
    "serial": "3314328158"
  },
  {
    "serial": "4828871865"
  },
  {
    "serial": "7517083361"
  },
  {
    "serial": "2660586054"
  },
  {
    "serial": "8178903442"
  },
  {
    "serial": "3049690567"
  },
  {
    "serial": "2084335815"
  },
  {
    "serial": "0634386130"
  },
  {
    "serial": "4916636394"
  },
  {
    "serial": "8169957977"
  },
  {
    "serial": "1480973823"
  },
  {
    "serial": "5226728920"
  },
  {
    "serial": "4286019189"
  },
  {
    "serial": "7208209390"
  },
  {
    "serial": "2675079020"
  },
  {
    "serial": "9892330698"
  },
  {
    "serial": "0766042014"
  },
  {
    "serial": "6914860587"
  },
  {
    "serial": "6944049458"
  },
  {
    "serial": "8859659636"
  },
  {
    "serial": "1825368754"
  },
  {
    "serial": "2135812796"
  },
  {
    "serial": "5018929900"
  },
  {
    "serial": "3821063124"
  },
  {
    "serial": "1168119947"
  },
  {
    "serial": "7028304173"
  },
  {
    "serial": "3225500697"
  },
  {
    "serial": "3707506675"
  },
  {
    "serial": "5628292327"
  },
  {
    "serial": "3875924320"
  },
  {
    "serial": "2721034771"
  },
  {
    "serial": "2559994385"
  },
  {
    "serial": "1368879811"
  },
  {
    "serial": "2709312389"
  },
  {
    "serial": "7189527133"
  },
  {
    "serial": "0381326370"
  },
  {
    "serial": "4411545959"
  },
  {
    "serial": "2064573641"
  },
  {
    "serial": "9446973902"
  },
  {
    "serial": "7926003430"
  },
  {
    "serial": "4810250623"
  },
  {
    "serial": "5361019556"
  },
  {
    "serial": "1079365944"
  },
  {
    "serial": "5214310798"
  },
  {
    "serial": "6365227351"
  },
  {
    "serial": "8683495710"
  },
  {
    "serial": "3011033515"
  },
  {
    "serial": "5068580546"
  },
  {
    "serial": "1903969614"
  },
  {
    "serial": "2650378181"
  },
  {
    "serial": "1481212759"
  },
  {
    "serial": "8043410789"
  },
  {
    "serial": "0595535782"
  },
  {
    "serial": "1041415256"
  },
  {
    "serial": "2956493486"
  },
  {
    "serial": "6535303728"
  },
  {
    "serial": "9657643269"
  },
  {
    "serial": "6481038898"
  },
  {
    "serial": "8042721079"
  },
  {
    "serial": "1395164955"
  },
  {
    "serial": "4146166840"
  },
  {
    "serial": "0736769365"
  },
  {
    "serial": "2272627692"
  },
  {
    "serial": "7334367120"
  },
  {
    "serial": "7908343929"
  },
  {
    "serial": "5478457145"
  },
  {
    "serial": "2656079353"
  },
  {
    "serial": "7245978221"
  },
  {
    "serial": "3936717887"
  },
  {
    "serial": "1356434645"
  },
  {
    "serial": "1151097233"
  },
  {
    "serial": "8457008210"
  },
  {
    "serial": "1168424610"
  },
  {
    "serial": "8049285730"
  },
  {
    "serial": "1653637270"
  },
  {
    "serial": "7965884781"
  },
  {
    "serial": "3091891758"
  },
  {
    "serial": "8465701491"
  },
  {
    "serial": "6790869454"
  },
  {
    "serial": "7298628350"
  },
  {
    "serial": "7518683490"
  },
  {
    "serial": "8136269779"
  },
  {
    "serial": "9715574290"
  },
  {
    "serial": "3743758306"
  },
  {
    "serial": "2623065444"
  },
  {
    "serial": "0149001968"
  },
  {
    "serial": "0189782600"
  },
  {
    "serial": "3131854949"
  },
  {
    "serial": "1839405261"
  },
  {
    "serial": "9227750776"
  },
  {
    "serial": "8556743782"
  },
  {
    "serial": "0491923207"
  },
  {
    "serial": "8805495960"
  },
  {
    "serial": "3421501796"
  },
  {
    "serial": "4088943511"
  },
  {
    "serial": "6801089910"
  },
  {
    "serial": "3796217747"
  },
  {
    "serial": "1552061655"
  },
  {
    "serial": "7729887328"
  },
  {
    "serial": "0745978148"
  },
  {
    "serial": "2149132173"
  },
  {
    "serial": "5826658469"
  },
  {
    "serial": "8348299945"
  },
  {
    "serial": "2193497977"
  },
  {
    "serial": "6693719665"
  },
  {
    "serial": "3043914393"
  },
  {
    "serial": "7861863483"
  },
  {
    "serial": "9253718259"
  },
  {
    "serial": "1747220679"
  },
  {
    "serial": "6582373897"
  },
  {
    "serial": "8640759166"
  },
  {
    "serial": "5249152967"
  },
  {
    "serial": "0620129296"
  },
  {
    "serial": "1410893554"
  },
  {
    "serial": "6587298461"
  },
  {
    "serial": "9602419963"
  },
  {
    "serial": "6103220759"
  },
  {
    "serial": "7111228057"
  },
  {
    "serial": "8086984708"
  },
  {
    "serial": "1497137974"
  },
  {
    "serial": "5062125934"
  },
  {
    "serial": "2636735256"
  },
  {
    "serial": "1700834573"
  },
  {
    "serial": "2413460524"
  },
  {
    "serial": "2976182291"
  },
  {
    "serial": "6232610474"
  },
  {
    "serial": "3444519817"
  },
  {
    "serial": "6686433555"
  },
  {
    "serial": "4988420727"
  },
  {
    "serial": "4874284203"
  },
  {
    "serial": "4064099130"
  },
  {
    "serial": "1819150903"
  },
  {
    "serial": "6639473914"
  },
  {
    "serial": "9633938387"
  },
  {
    "serial": "1583677941"
  },
  {
    "serial": "5273256403"
  },
  {
    "serial": "2086682792"
  },
  {
    "serial": "9216409962"
  },
  {
    "serial": "7949760941"
  },
  {
    "serial": "2040001204"
  },
  {
    "serial": "9421894974"
  },
  {
    "serial": "6258954947"
  },
  {
    "serial": "8187517225"
  },
  {
    "serial": "7443380733"
  },
  {
    "serial": "9917444722"
  },
  {
    "serial": "9710569022"
  },
  {
    "serial": "9047238739"
  },
  {
    "serial": "0690853072"
  },
  {
    "serial": "6903518410"
  },
  {
    "serial": "3103347021"
  },
  {
    "serial": "8436674801"
  },
  {
    "serial": "9872796900"
  },
  {
    "serial": "0505336594"
  },
  {
    "serial": "4668808084"
  },
  {
    "serial": "5560756982"
  },
  {
    "serial": "2906482837"
  },
  {
    "serial": "2823218512"
  },
  {
    "serial": "6280723120"
  },
  {
    "serial": "3744125299"
  },
  {
    "serial": "9819339897"
  },
  {
    "serial": "8656900985"
  },
  {
    "serial": "5289262528"
  },
  {
    "serial": "7504608139"
  },
  {
    "serial": "3746487879"
  },
  {
    "serial": "8780218874"
  },
  {
    "serial": "9687747890"
  },
  {
    "serial": "7150179674"
  },
  {
    "serial": "8635310728"
  },
  {
    "serial": "5657659297"
  },
  {
    "serial": "2545951564"
  },
  {
    "serial": "7638132691"
  },
  {
    "serial": "3835305883"
  },
  {
    "serial": "1232876605"
  },
  {
    "serial": "2938772080"
  },
  {
    "serial": "1984643971"
  },
  {
    "serial": "5075369511"
  },
  {
    "serial": "4040539514"
  },
  {
    "serial": "1624385595"
  },
  {
    "serial": "9201441525"
  },
  {
    "serial": "8247305512"
  },
  {
    "serial": "6610602580"
  },
  {
    "serial": "3531995268"
  },
  {
    "serial": "0037315520"
  },
  {
    "serial": "1203993405"
  },
  {
    "serial": "6127111836"
  },
  {
    "serial": "3870097536"
  },
  {
    "serial": "7417229916"
  },
  {
    "serial": "6819248557"
  },
  {
    "serial": "3115357851"
  },
  {
    "serial": "5787094092"
  },
  {
    "serial": "9624084969"
  },
  {
    "serial": "7572432834"
  },
  {
    "serial": "4894328592"
  },
  {
    "serial": "2894087366"
  },
  {
    "serial": "7924093565"
  },
  {
    "serial": "7389914735"
  },
  {
    "serial": "6582851868"
  },
  {
    "serial": "2252898578"
  },
  {
    "serial": "7224223193"
  },
  {
    "serial": "9291909134"
  },
  {
    "serial": "9782819412"
  },
  {
    "serial": "8119611286"
  },
  {
    "serial": "2504600012"
  },
  {
    "serial": "7751754479"
  },
  {
    "serial": "6558884042"
  },
  {
    "serial": "2824737221"
  },
  {
    "serial": "6588699782"
  },
  {
    "serial": "7452178168"
  },
  {
    "serial": "7295331487"
  },
  {
    "serial": "1961838248"
  },
  {
    "serial": "4986945162"
  },
  {
    "serial": "2530289798"
  },
  {
    "serial": "1819549252"
  },
  {
    "serial": "4283894808"
  },
  {
    "serial": "1658644560"
  },
  {
    "serial": "8315235831"
  },
  {
    "serial": "7830747627"
  },
  {
    "serial": "1527794497"
  },
  {
    "serial": "9236064748"
  },
  {
    "serial": "4347006845"
  },
  {
    "serial": "1415835204"
  },
  {
    "serial": "5158066679"
  },
  {
    "serial": "2221104884"
  },
  {
    "serial": "7416259518"
  },
  {
    "serial": "7019928667"
  },
  {
    "serial": "1773964950"
  },
  {
    "serial": "7908647204"
  },
  {
    "serial": "1122830290"
  },
  {
    "serial": "4489813263"
  },
  {
    "serial": "8207099840"
  },
  {
    "serial": "9702708950"
  },
  {
    "serial": "7332805626"
  },
  {
    "serial": "2502508761"
  },
  {
    "serial": "8293208693"
  },
  {
    "serial": "4424110320"
  },
  {
    "serial": "4990383657"
  },
  {
    "serial": "6790684119"
  },
  {
    "serial": "6702277630"
  },
  {
    "serial": "8754611047"
  },
  {
    "serial": "0903582351"
  },
  {
    "serial": "2818283794"
  },
  {
    "serial": "5103422373"
  },
  {
    "serial": "5767174203"
  },
  {
    "serial": "8407040701"
  },
  {
    "serial": "6947037500"
  },
  {
    "serial": "6455354438"
  },
  {
    "serial": "7203666073"
  },
  {
    "serial": "0675225395"
  },
  {
    "serial": "1571464146"
  },
  {
    "serial": "3164096459"
  },
  {
    "serial": "7247554731"
  },
  {
    "serial": "5377842447"
  },
  {
    "serial": "0834639916"
  },
  {
    "serial": "8852163313"
  },
  {
    "serial": "2822295081"
  },
  {
    "serial": "5803129617"
  },
  {
    "serial": "1449916269"
  },
  {
    "serial": "7443447714"
  },
  {
    "serial": "7503716230"
  },
  {
    "serial": "9365757153"
  },
  {
    "serial": "1610441451"
  },
  {
    "serial": "2051553903"
  },
  {
    "serial": "0890011919"
  },
  {
    "serial": "6894460069"
  },
  {
    "serial": "1515743613"
  },
  {
    "serial": "6248146638"
  },
  {
    "serial": "8496579486"
  },
  {
    "serial": "3563388416"
  },
  {
    "serial": "7063553064"
  },
  {
    "serial": "6304322388"
  },
  {
    "serial": "3716402122"
  },
  {
    "serial": "2593425941"
  },
  {
    "serial": "2726264639"
  },
  {
    "serial": "4624191005"
  },
  {
    "serial": "2551101856"
  },
  {
    "serial": "3581005745"
  },
  {
    "serial": "4794829590"
  },
  {
    "serial": "4286514395"
  },
  {
    "serial": "6630639455"
  },
  {
    "serial": "8573425587"
  },
  {
    "serial": "9849379814"
  },
  {
    "serial": "1404198119"
  },
  {
    "serial": "5979557930"
  },
  {
    "serial": "0618360374"
  },
  {
    "serial": "9533207586"
  },
  {
    "serial": "5465243268"
  },
  {
    "serial": "2542080854"
  },
  {
    "serial": "7940819639"
  },
  {
    "serial": "1281124659"
  },
  {
    "serial": "1692861626"
  },
  {
    "serial": "8913522192"
  },
  {
    "serial": "4968766644"
  },
  {
    "serial": "9798166873"
  },
  {
    "serial": "3777313051"
  },
  {
    "serial": "7694202339"
  },
  {
    "serial": "4443741618"
  },
  {
    "serial": "6090242600"
  },
  {
    "serial": "0740666870"
  },
  {
    "serial": "1667504003"
  },
  {
    "serial": "0914085295"
  },
  {
    "serial": "9443852513"
  },
  {
    "serial": "8899334463"
  },
  {
    "serial": "7797977225"
  },
  {
    "serial": "4003644665"
  },
  {
    "serial": "5635420127"
  },
  {
    "serial": "1788611513"
  },
  {
    "serial": "3475249987"
  },
  {
    "serial": "3356662019"
  },
  {
    "serial": "6448350949"
  },
  {
    "serial": "2283795959"
  },
  {
    "serial": "4646429458"
  },
  {
    "serial": "5669771395"
  },
  {
    "serial": "2450270588"
  },
  {
    "serial": "4054833373"
  },
  {
    "serial": "6105393554"
  },
  {
    "serial": "4303770038"
  },
  {
    "serial": "8514139115"
  },
  {
    "serial": "0399422393"
  },
  {
    "serial": "2912604762"
  },
  {
    "serial": "5822120431"
  },
  {
    "serial": "1213018979"
  },
  {
    "serial": "8354278197"
  },
  {
    "serial": "9307056870"
  },
  {
    "serial": "3986818064"
  },
  {
    "serial": "1640448476"
  },
  {
    "serial": "9358330869"
  },
  {
    "serial": "3023863008"
  },
  {
    "serial": "9619184634"
  },
  {
    "serial": "9412514136"
  },
  {
    "serial": "2577947076"
  },
  {
    "serial": "1686429463"
  },
  {
    "serial": "4955129780"
  },
  {
    "serial": "2077994099"
  },
  {
    "serial": "5520045518"
  },
  {
    "serial": "6273120813"
  },
  {
    "serial": "9679110875"
  },
  {
    "serial": "4842467864"
  },
  {
    "serial": "5257552918"
  },
  {
    "serial": "1483426290"
  },
  {
    "serial": "8625777910"
  },
  {
    "serial": "5174865807"
  },
  {
    "serial": "3979015637"
  },
  {
    "serial": "6515645965"
  },
  {
    "serial": "5375231023"
  },
  {
    "serial": "7806914896"
  },
  {
    "serial": "7070990366"
  },
  {
    "serial": "8891214119"
  },
  {
    "serial": "4902339524"
  },
  {
    "serial": "4162544284"
  },
  {
    "serial": "9475548476"
  },
  {
    "serial": "9963864450"
  },
  {
    "serial": "1434753453"
  },
  {
    "serial": "0117681163"
  },
  {
    "serial": "6264892883"
  },
  {
    "serial": "9114421507"
  },
  {
    "serial": "5142469559"
  },
  {
    "serial": "7586833811"
  },
  {
    "serial": "1728629518"
  },
  {
    "serial": "2223479920"
  },
  {
    "serial": "7531494206"
  },
  {
    "serial": "1527434003"
  },
  {
    "serial": "1148421280"
  },
  {
    "serial": "1862157383"
  },
  {
    "serial": "1283986931"
  },
  {
    "serial": "2270407444"
  },
  {
    "serial": "9812834829"
  },
  {
    "serial": "4473614818"
  },
  {
    "serial": "0478018450"
  },
  {
    "serial": "0545943284"
  },
  {
    "serial": "3484774744"
  },
  {
    "serial": "8841668612"
  },
  {
    "serial": "7618626951"
  },
  {
    "serial": "7990493418"
  },
  {
    "serial": "8093026451"
  },
  {
    "serial": "5319140397"
  },
  {
    "serial": "1570211613"
  },
  {
    "serial": "5183680940"
  },
  {
    "serial": "5949741069"
  },
  {
    "serial": "0064094097"
  },
  {
    "serial": "4905272482"
  },
  {
    "serial": "3356073233"
  },
  {
    "serial": "6771788921"
  },
  {
    "serial": "2865157974"
  },
  {
    "serial": "4607635721"
  },
  {
    "serial": "6011459739"
  },
  {
    "serial": "9357485631"
  },
  {
    "serial": "0563523893"
  },
  {
    "serial": "0860714484"
  },
  {
    "serial": "0997983499"
  },
  {
    "serial": "2883165645"
  },
  {
    "serial": "3093440802"
  },
  {
    "serial": "2658340886"
  },
  {
    "serial": "9805295889"
  },
  {
    "serial": "8333701350"
  },
  {
    "serial": "7338721140"
  },
  {
    "serial": "4833061478"
  },
  {
    "serial": "4377803624"
  },
  {
    "serial": "3747722381"
  },
  {
    "serial": "4872307816"
  },
  {
    "serial": "6629113140"
  },
  {
    "serial": "3847318627"
  },
  {
    "serial": "3064525714"
  },
  {
    "serial": "1314894492"
  },
  {
    "serial": "0576185425"
  },
  {
    "serial": "9730653756"
  },
  {
    "serial": "6723107139"
  },
  {
    "serial": "2700068055"
  },
  {
    "serial": "9326279024"
  },
  {
    "serial": "9906333969"
  },
  {
    "serial": "2828641106"
  },
  {
    "serial": "8311367810"
  },
  {
    "serial": "7356272471"
  },
  {
    "serial": "6928783098"
  },
  {
    "serial": "5920098919"
  },
  {
    "serial": "7365490940"
  },
  {
    "serial": "8763593210"
  },
  {
    "serial": "8504435317"
  },
  {
    "serial": "5656891511"
  },
  {
    "serial": "5385422505"
  },
  {
    "serial": "1972270050"
  },
  {
    "serial": "7637932851"
  },
  {
    "serial": "5518689657"
  },
  {
    "serial": "4073149603"
  },
  {
    "serial": "4239199310"
  },
  {
    "serial": "0247543549"
  },
  {
    "serial": "6397369734"
  },
  {
    "serial": "4353732789"
  },
  {
    "serial": "6146785735"
  },
  {
    "serial": "4924854716"
  },
  {
    "serial": "3493663177"
  },
  {
    "serial": "6591363038"
  },
  {
    "serial": "0632839379"
  },
  {
    "serial": "5551323057"
  },
  {
    "serial": "3159886286"
  },
  {
    "serial": "7272530531"
  },
  {
    "serial": "5591913107"
  },
  {
    "serial": "6122713982"
  },
  {
    "serial": "6256646263"
  },
  {
    "serial": "8020488600"
  },
  {
    "serial": "2080860238"
  },
  {
    "serial": "6369727687"
  },
  {
    "serial": "9522075564"
  },
  {
    "serial": "8697807264"
  },
  {
    "serial": "5124543033"
  },
  {
    "serial": "5712164895"
  },
  {
    "serial": "9959204828"
  },
  {
    "serial": "2778165551"
  },
  {
    "serial": "3461391025"
  },
  {
    "serial": "0558071882"
  },
  {
    "serial": "8546012058"
  },
  {
    "serial": "4852197872"
  },
  {
    "serial": "8991086490"
  },
  {
    "serial": "4990004220"
  },
  {
    "serial": "3743526265"
  },
  {
    "serial": "0689577385"
  },
  {
    "serial": "8116987614"
  },
  {
    "serial": "4673045383"
  },
  {
    "serial": "0478292998"
  },
  {
    "serial": "6619519827"
  },
  {
    "serial": "9875412109"
  },
  {
    "serial": "0549022663"
  },
  {
    "serial": "7645436812"
  },
  {
    "serial": "4958126700"
  },
  {
    "serial": "9555821736"
  },
  {
    "serial": "7471685227"
  },
  {
    "serial": "1421268713"
  },
  {
    "serial": "8811329195"
  },
  {
    "serial": "7251231374"
  },
  {
    "serial": "9743223407"
  },
  {
    "serial": "6713341748"
  },
  {
    "serial": "7950851787"
  },
  {
    "serial": "7465081631"
  },
  {
    "serial": "9423078089"
  },
  {
    "serial": "6154565508"
  },
  {
    "serial": "4569016365"
  },
  {
    "serial": "0443882873"
  },
  {
    "serial": "9713916170"
  },
  {
    "serial": "9253911243"
  },
  {
    "serial": "6120667172"
  },
  {
    "serial": "9585261648"
  },
  {
    "serial": "7333131428"
  },
  {
    "serial": "4930080231"
  },
  {
    "serial": "5954540984"
  },
  {
    "serial": "8042798044"
  },
  {
    "serial": "9767352397"
  },
  {
    "serial": "8474150094"
  },
  {
    "serial": "0470371394"
  },
  {
    "serial": "8425939074"
  },
  {
    "serial": "5003652152"
  },
  {
    "serial": "9614316819"
  },
  {
    "serial": "6621565636"
  },
  {
    "serial": "6912582514"
  },
  {
    "serial": "1184504403"
  },
  {
    "serial": "8177213306"
  },
  {
    "serial": "0525267886"
  },
  {
    "serial": "9911907294"
  },
  {
    "serial": "1710488485"
  },
  {
    "serial": "5020750724"
  },
  {
    "serial": "3899067510"
  },
  {
    "serial": "1317616470"
  },
  {
    "serial": "1243954755"
  },
  {
    "serial": "4988062636"
  },
  {
    "serial": "3345666899"
  },
  {
    "serial": "1920308135"
  },
  {
    "serial": "2220392613"
  },
  {
    "serial": "2191671433"
  },
  {
    "serial": "9324381541"
  },
  {
    "serial": "4446565691"
  },
  {
    "serial": "2763806631"
  },
  {
    "serial": "8475915644"
  },
  {
    "serial": "8939108513"
  },
  {
    "serial": "7133864806"
  },
  {
    "serial": "2118212204"
  },
  {
    "serial": "5541162060"
  },
  {
    "serial": "4280374374"
  },
  {
    "serial": "6146312480"
  },
  {
    "serial": "9899392501"
  },
  {
    "serial": "0123230286"
  },
  {
    "serial": "3044096067"
  },
  {
    "serial": "4973330378"
  },
  {
    "serial": "3436506806"
  },
  {
    "serial": "6821026157"
  },
  {
    "serial": "1647071644"
  },
  {
    "serial": "2640927758"
  },
  {
    "serial": "6702816395"
  },
  {
    "serial": "9798239019"
  },
  {
    "serial": "0332163542"
  },
  {
    "serial": "3438118485"
  },
  {
    "serial": "8143603432"
  },
  {
    "serial": "6399537056"
  },
  {
    "serial": "8614557026"
  },
  {
    "serial": "1620655710"
  },
  {
    "serial": "7589290506"
  },
  {
    "serial": "8693332929"
  },
  {
    "serial": "6937594189"
  },
  {
    "serial": "9141042193"
  },
  {
    "serial": "1602570424"
  },
  {
    "serial": "3434077867"
  },
  {
    "serial": "5535363740"
  },
  {
    "serial": "8208689698"
  },
  {
    "serial": "6519067307"
  },
  {
    "serial": "7356886916"
  },
  {
    "serial": "8689215245"
  },
  {
    "serial": "3564149882"
  },
  {
    "serial": "4241043902"
  },
  {
    "serial": "8963821759"
  },
  {
    "serial": "3184765927"
  },
  {
    "serial": "9220606827"
  },
  {
    "serial": "6163698936"
  },
  {
    "serial": "0889446563"
  },
  {
    "serial": "6157198133"
  },
  {
    "serial": "3586635728"
  },
  {
    "serial": "4081773857"
  },
  {
    "serial": "3160299727"
  },
  {
    "serial": "3725931012"
  },
  {
    "serial": "5934346148"
  },
  {
    "serial": "7501830470"
  },
  {
    "serial": "4178895092"
  },
  {
    "serial": "1730680608"
  },
  {
    "serial": "0734233455"
  },
  {
    "serial": "2200982359"
  },
  {
    "serial": "6013454753"
  },
  {
    "serial": "5867914235"
  },
  {
    "serial": "0487676702"
  },
  {
    "serial": "7331122551"
  },
  {
    "serial": "1019669108"
  },
  {
    "serial": "7726337905"
  },
  {
    "serial": "5434097522"
  },
  {
    "serial": "6860475414"
  },
  {
    "serial": "9685778624"
  },
  {
    "serial": "8963647907"
  },
  {
    "serial": "8161876142"
  },
  {
    "serial": "1365794880"
  },
  {
    "serial": "6756401607"
  },
  {
    "serial": "8589012734"
  },
  {
    "serial": "5307681998"
  },
  {
    "serial": "4490091347"
  },
  {
    "serial": "4918751159"
  },
  {
    "serial": "2371517000"
  },
  {
    "serial": "2971516733"
  },
  {
    "serial": "8290942914"
  },
  {
    "serial": "9273300211"
  },
  {
    "serial": "4318538388"
  },
  {
    "serial": "5668465809"
  },
  {
    "serial": "4219837723"
  },
  {
    "serial": "5924515272"
  },
  {
    "serial": "1087437248"
  },
  {
    "serial": "1963133432"
  },
  {
    "serial": "0998595524"
  },
  {
    "serial": "2192848154"
  },
  {
    "serial": "9940862593"
  },
  {
    "serial": "3708512649"
  },
  {
    "serial": "8078331959"
  },
  {
    "serial": "7292243339"
  },
  {
    "serial": "9585405203"
  },
  {
    "serial": "3896133125"
  },
  {
    "serial": "1066222132"
  },
  {
    "serial": "8628478896"
  },
  {
    "serial": "6102443972"
  },
  {
    "serial": "0630525384"
  },
  {
    "serial": "5589285179"
  },
  {
    "serial": "6541554140"
  },
  {
    "serial": "0097580120"
  },
  {
    "serial": "6335386048"
  },
  {
    "serial": "1092655990"
  },
  {
    "serial": "9106943435"
  },
  {
    "serial": "3136837105"
  },
  {
    "serial": "0908699366"
  },
  {
    "serial": "8765963221"
  },
  {
    "serial": "1507957924"
  },
  {
    "serial": "4410343810"
  },
  {
    "serial": "1984306017"
  },
  {
    "serial": "2719092286"
  },
  {
    "serial": "7618770247"
  },
  {
    "serial": "2673462301"
  },
  {
    "serial": "8680714261"
  },
  {
    "serial": "2940565480"
  },
  {
    "serial": "6907131012"
  },
  {
    "serial": "7619546166"
  },
  {
    "serial": "6196794058"
  },
  {
    "serial": "5296978785"
  },
  {
    "serial": "0001534841"
  },
  {
    "serial": "7543122696"
  },
  {
    "serial": "3067423164"
  },
  {
    "serial": "3212341923"
  },
  {
    "serial": "5896057642"
  },
  {
    "serial": "1979911003"
  },
  {
    "serial": "0991025206"
  },
  {
    "serial": "3677578159"
  },
  {
    "serial": "6097261736"
  },
  {
    "serial": "3894854029"
  },
  {
    "serial": "5969212116"
  },
  {
    "serial": "5340629889"
  },
  {
    "serial": "0792891269"
  },
  {
    "serial": "1413140276"
  },
  {
    "serial": "9773689261"
  },
  {
    "serial": "9697168996"
  },
  {
    "serial": "1209656519"
  },
  {
    "serial": "9054940185"
  },
  {
    "serial": "7099694361"
  },
  {
    "serial": "3161758440"
  },
  {
    "serial": "5880060784"
  },
  {
    "serial": "4487612121"
  },
  {
    "serial": "1093748182"
  },
  {
    "serial": "7113036854"
  },
  {
    "serial": "8282422925"
  },
  {
    "serial": "1493485955"
  },
  {
    "serial": "1477955601"
  },
  {
    "serial": "9980499850"
  },
  {
    "serial": "6152519168"
  },
  {
    "serial": "1751470905"
  },
  {
    "serial": "1683129769"
  },
  {
    "serial": "9330356552"
  },
  {
    "serial": "3638404925"
  },
  {
    "serial": "2737292116"
  },
  {
    "serial": "2466774508"
  },
  {
    "serial": "0130668213"
  },
  {
    "serial": "4595879505"
  },
  {
    "serial": "8676135653"
  },
  {
    "serial": "0978843605"
  },
  {
    "serial": "6019797718"
  },
  {
    "serial": "4835427388"
  },
  {
    "serial": "2543768127"
  },
  {
    "serial": "7038395773"
  },
  {
    "serial": "2417315724"
  },
  {
    "serial": "0243763786"
  },
  {
    "serial": "7301721556"
  },
  {
    "serial": "3180491056"
  },
  {
    "serial": "8182703283"
  },
  {
    "serial": "6623181366"
  },
  {
    "serial": "0869058537"
  },
  {
    "serial": "7770122146"
  },
  {
    "serial": "3236322974"
  },
  {
    "serial": "3222239885"
  },
  {
    "serial": "4784614234"
  },
  {
    "serial": "8698194647"
  },
  {
    "serial": "3951596703"
  },
  {
    "serial": "0722069473"
  },
  {
    "serial": "2986461529"
  },
  {
    "serial": "2009718863"
  },
  {
    "serial": "8326304717"
  },
  {
    "serial": "8542701902"
  },
  {
    "serial": "6735795731"
  },
  {
    "serial": "1309471546"
  },
  {
    "serial": "3769162581"
  },
  {
    "serial": "7608512062"
  },
  {
    "serial": "6897013121"
  },
  {
    "serial": "7767648590"
  },
  {
    "serial": "8934949010"
  },
  {
    "serial": "3123144846"
  },
  {
    "serial": "5753190106"
  },
  {
    "serial": "5929608270"
  },
  {
    "serial": "8354751029"
  },
  {
    "serial": "1240760973"
  },
  {
    "serial": "7517294471"
  },
  {
    "serial": "9816360656"
  },
  {
    "serial": "2803481825"
  },
  {
    "serial": "2368162554"
  },
  {
    "serial": "6129902653"
  },
  {
    "serial": "5466889531"
  },
  {
    "serial": "1995771670"
  },
  {
    "serial": "2980634162"
  },
  {
    "serial": "6857802158"
  },
  {
    "serial": "8935629298"
  },
  {
    "serial": "4078587799"
  },
  {
    "serial": "4660693187"
  },
  {
    "serial": "4646576183"
  },
  {
    "serial": "4805089887"
  },
  {
    "serial": "1158519668"
  },
  {
    "serial": "4344847068"
  },
  {
    "serial": "2940905991"
  },
  {
    "serial": "2802572467"
  },
  {
    "serial": "0142416676"
  },
  {
    "serial": "1491557664"
  },
  {
    "serial": "1829710845"
  },
  {
    "serial": "0278868948"
  },
  {
    "serial": "7841426617"
  },
  {
    "serial": "8213026944"
  },
  {
    "serial": "0572922110"
  },
  {
    "serial": "9944036020"
  },
  {
    "serial": "9680739571"
  },
  {
    "serial": "6115985837"
  },
  {
    "serial": "8810449549"
  },
  {
    "serial": "2009006251"
  },
  {
    "serial": "5256566729"
  },
  {
    "serial": "2179478926"
  },
  {
    "serial": "8662734493"
  },
  {
    "serial": "3329262293"
  },
  {
    "serial": "5911497260"
  },
  {
    "serial": "3193649328"
  },
  {
    "serial": "1050916178"
  },
  {
    "serial": "9098099352"
  },
  {
    "serial": "3489105852"
  },
  {
    "serial": "0224339747"
  },
  {
    "serial": "1188548653"
  },
  {
    "serial": "3451619237"
  },
  {
    "serial": "5831977938"
  },
  {
    "serial": "7676159481"
  },
  {
    "serial": "2566246571"
  },
  {
    "serial": "4916697669"
  },
  {
    "serial": "5190126812"
  },
  {
    "serial": "0103213500"
  },
  {
    "serial": "7628192713"
  },
  {
    "serial": "0781753629"
  },
  {
    "serial": "2091641809"
  },
  {
    "serial": "2342955545"
  },
  {
    "serial": "7262489151"
  },
  {
    "serial": "6777607141"
  },
  {
    "serial": "5183399004"
  },
  {
    "serial": "0243447224"
  },
  {
    "serial": "0491663548"
  },
  {
    "serial": "0822856084"
  },
  {
    "serial": "3172205134"
  },
  {
    "serial": "8812120924"
  },
  {
    "serial": "7018474358"
  },
  {
    "serial": "3695044390"
  },
  {
    "serial": "2423842125"
  },
  {
    "serial": "4157112220"
  },
  {
    "serial": "0144407442"
  },
  {
    "serial": "1330539386"
  },
  {
    "serial": "0080063084"
  },
  {
    "serial": "3704537731"
  },
  {
    "serial": "5840754211"
  },
  {
    "serial": "5301269873"
  },
  {
    "serial": "6188234881"
  },
  {
    "serial": "5113467939"
  },
  {
    "serial": "3881721736"
  },
  {
    "serial": "5661391754"
  },
  {
    "serial": "4640853422"
  },
  {
    "serial": "8136442475"
  },
  {
    "serial": "8865724846"
  },
  {
    "serial": "6384773062"
  },
  {
    "serial": "4626733010"
  },
  {
    "serial": "2235781149"
  },
  {
    "serial": "0393477492"
  },
  {
    "serial": "2671963821"
  },
  {
    "serial": "4137135556"
  },
  {
    "serial": "4034769234"
  },
  {
    "serial": "6728116119"
  },
  {
    "serial": "9588693789"
  },
  {
    "serial": "5533782594"
  },
  {
    "serial": "2657609414"
  },
  {
    "serial": "3941912515"
  },
  {
    "serial": "8733972825"
  },
  {
    "serial": "7812364714"
  },
  {
    "serial": "4487357370"
  },
  {
    "serial": "6700874446"
  },
  {
    "serial": "9392265857"
  },
  {
    "serial": "9920833440"
  },
  {
    "serial": "9199687766"
  },
  {
    "serial": "8159154460"
  },
  {
    "serial": "3483129411"
  },
  {
    "serial": "6701552355"
  },
  {
    "serial": "2514919527"
  },
  {
    "serial": "0413246364"
  },
  {
    "serial": "0473314433"
  },
  {
    "serial": "8719376876"
  },
  {
    "serial": "2462939816"
  },
  {
    "serial": "3693289989"
  },
  {
    "serial": "9964899851"
  },
  {
    "serial": "7115901022"
  },
  {
    "serial": "9001429837"
  },
  {
    "serial": "3367294463"
  },
  {
    "serial": "3607282013"
  },
  {
    "serial": "0937982312"
  },
  {
    "serial": "6462825412"
  },
  {
    "serial": "2592357160"
  },
  {
    "serial": "4021053204"
  },
  {
    "serial": "2004317984"
  },
  {
    "serial": "7882967230"
  },
  {
    "serial": "9550885173"
  },
  {
    "serial": "5090715599"
  },
  {
    "serial": "3510101409"
  },
  {
    "serial": "7055025469"
  },
  {
    "serial": "8870441675"
  },
  {
    "serial": "1718847344"
  },
  {
    "serial": "9928208231"
  },
  {
    "serial": "7507935018"
  },
  {
    "serial": "1849469935"
  },
  {
    "serial": "1670266665"
  },
  {
    "serial": "3296862851"
  },
  {
    "serial": "8068840423"
  },
  {
    "serial": "2874228196"
  },
  {
    "serial": "2035993787"
  },
  {
    "serial": "7372821764"
  },
  {
    "serial": "9824047097"
  },
  {
    "serial": "7945744857"
  },
  {
    "serial": "5429858102"
  },
  {
    "serial": "8293711274"
  },
  {
    "serial": "8015520656"
  },
  {
    "serial": "8617592616"
  },
  {
    "serial": "4435498821"
  },
  {
    "serial": "0431047414"
  },
  {
    "serial": "1321342394"
  },
  {
    "serial": "2390141774"
  },
  {
    "serial": "3907325017"
  },
  {
    "serial": "6587451391"
  },
  {
    "serial": "7418128935"
  },
  {
    "serial": "5766426455"
  },
  {
    "serial": "6408611868"
  },
  {
    "serial": "2369882960"
  },
  {
    "serial": "8176074170"
  },
  {
    "serial": "2323380408"
  },
  {
    "serial": "1652363605"
  },
  {
    "serial": "7760459987"
  },
  {
    "serial": "8586811716"
  },
  {
    "serial": "4191643263"
  },
  {
    "serial": "4300730571"
  },
  {
    "serial": "8729640089"
  },
  {
    "serial": "6425401418"
  },
  {
    "serial": "8154243441"
  },
  {
    "serial": "2701635787"
  },
  {
    "serial": "8733866290"
  },
  {
    "serial": "2040022515"
  },
  {
    "serial": "5515704681"
  },
  {
    "serial": "9378386123"
  },
  {
    "serial": "2862112543"
  },
  {
    "serial": "5399664704"
  },
  {
    "serial": "9836921909"
  },
  {
    "serial": "8475058254"
  },
  {
    "serial": "2621593009"
  },
  {
    "serial": "0790946438"
  },
  {
    "serial": "4528476189"
  },
  {
    "serial": "5276958526"
  },
  {
    "serial": "7762700081"
  },
  {
    "serial": "2186399792"
  },
  {
    "serial": "2577166164"
  },
  {
    "serial": "3500842467"
  },
  {
    "serial": "4454946049"
  },
  {
    "serial": "5989378475"
  },
  {
    "serial": "8483787548"
  },
  {
    "serial": "5331647841"
  },
  {
    "serial": "1332197076"
  },
  {
    "serial": "6294469702"
  },
  {
    "serial": "3570311476"
  },
  {
    "serial": "9498118331"
  },
  {
    "serial": "7033352639"
  },
  {
    "serial": "6087067853"
  },
  {
    "serial": "4822644458"
  },
  {
    "serial": "1458172101"
  },
  {
    "serial": "6502654889"
  },
  {
    "serial": "1105657603"
  },
  {
    "serial": "9351116505"
  },
  {
    "serial": "9095883808"
  },
  {
    "serial": "9140471005"
  },
  {
    "serial": "3965275443"
  },
  {
    "serial": "3149116760"
  },
  {
    "serial": "2536168277"
  },
  {
    "serial": "7405359113"
  },
  {
    "serial": "5667066772"
  },
  {
    "serial": "7071283480"
  },
  {
    "serial": "7942837019"
  },
  {
    "serial": "3221105319"
  },
  {
    "serial": "3101708406"
  },
  {
    "serial": "2274241435"
  },
  {
    "serial": "4017741226"
  },
  {
    "serial": "1617958515"
  },
  {
    "serial": "3181500970"
  },
  {
    "serial": "1762493953"
  },
  {
    "serial": "7507932056"
  },
  {
    "serial": "0941688525"
  },
  {
    "serial": "5388826736"
  },
  {
    "serial": "5644397464"
  },
  {
    "serial": "9725905187"
  },
  {
    "serial": "9613829267"
  },
  {
    "serial": "3504144605"
  },
  {
    "serial": "3616493049"
  },
  {
    "serial": "1261430423"
  },
  {
    "serial": "5234117710"
  },
  {
    "serial": "7785452488"
  },
  {
    "serial": "6006397704"
  },
  {
    "serial": "6339003169"
  },
  {
    "serial": "7618293513"
  },
  {
    "serial": "0518103726"
  },
  {
    "serial": "3947042861"
  },
  {
    "serial": "7162146372"
  },
  {
    "serial": "2016443323"
  },
  {
    "serial": "2265059879"
  },
  {
    "serial": "6295414152"
  },
  {
    "serial": "1744961101"
  },
  {
    "serial": "8726240388"
  },
  {
    "serial": "8785057665"
  },
  {
    "serial": "5683745896"
  },
  {
    "serial": "9546860785"
  },
  {
    "serial": "6684614396"
  },
  {
    "serial": "3527614576"
  },
  {
    "serial": "5920620068"
  },
  {
    "serial": "6415911988"
  },
  {
    "serial": "7614419716"
  },
  {
    "serial": "7853042104"
  },
  {
    "serial": "6319717374"
  },
  {
    "serial": "2077641930"
  },
  {
    "serial": "7102845869"
  },
  {
    "serial": "9905593951"
  },
  {
    "serial": "8828755515"
  },
  {
    "serial": "8198733662"
  },
  {
    "serial": "0625848171"
  },
  {
    "serial": "3226124430"
  },
  {
    "serial": "6162585944"
  },
  {
    "serial": "3019415854"
  },
  {
    "serial": "6341115613"
  },
  {
    "serial": "8413341531"
  },
  {
    "serial": "3001757867"
  },
  {
    "serial": "8211147700"
  },
  {
    "serial": "8227398073"
  },
  {
    "serial": "7221314540"
  },
  {
    "serial": "1423926177"
  },
  {
    "serial": "6617997504"
  },
  {
    "serial": "6705654876"
  },
  {
    "serial": "0632884029"
  },
  {
    "serial": "3607097460"
  },
  {
    "serial": "4181772353"
  },
  {
    "serial": "1096218308"
  },
  {
    "serial": "1829281789"
  },
  {
    "serial": "8680498998"
  },
  {
    "serial": "4293471068"
  },
  {
    "serial": "4491269488"
  },
  {
    "serial": "5999535866"
  },
  {
    "serial": "2132093077"
  },
  {
    "serial": "4602352645"
  },
  {
    "serial": "4026767717"
  },
  {
    "serial": "0251206991"
  },
  {
    "serial": "9030187448"
  },
  {
    "serial": "7595552329"
  },
  {
    "serial": "3004109355"
  },
  {
    "serial": "7914932244"
  },
  {
    "serial": "8351919330"
  },
  {
    "serial": "8634202090"
  },
  {
    "serial": "7600468974"
  },
  {
    "serial": "6970025794"
  },
  {
    "serial": "7297334711"
  },
  {
    "serial": "0354834731"
  },
  {
    "serial": "5084840734"
  },
  {
    "serial": "7775673879"
  },
  {
    "serial": "5238765704"
  },
  {
    "serial": "5707639455"
  },
  {
    "serial": "5577468514"
  },
  {
    "serial": "6924771865"
  },
  {
    "serial": "5536875999"
  },
  {
    "serial": "3589559727"
  },
  {
    "serial": "6073675396"
  },
  {
    "serial": "4857881736"
  },
  {
    "serial": "8147726791"
  },
  {
    "serial": "6659094624"
  },
  {
    "serial": "3925899068"
  },
  {
    "serial": "2949571919"
  },
  {
    "serial": "5799926679"
  },
  {
    "serial": "7132969481"
  },
  {
    "serial": "6056295899"
  },
  {
    "serial": "2045004526"
  },
  {
    "serial": "8993434292"
  },
  {
    "serial": "8417202655"
  },
  {
    "serial": "9983460677"
  },
  {
    "serial": "9298785396"
  },
  {
    "serial": "0449935444"
  },
  {
    "serial": "4272137995"
  },
  {
    "serial": "3617667252"
  },
  {
    "serial": "3898897396"
  },
  {
    "serial": "4099284319"
  },
  {
    "serial": "2203097205"
  },
  {
    "serial": "3124828157"
  },
  {
    "serial": "9516433225"
  },
  {
    "serial": "4886486168"
  },
  {
    "serial": "1798225957"
  },
  {
    "serial": "6068291936"
  },
  {
    "serial": "7169433534"
  },
  {
    "serial": "8705156019"
  },
  {
    "serial": "8471302318"
  },
  {
    "serial": "6498568291"
  },
  {
    "serial": "1684357708"
  },
  {
    "serial": "7477346402"
  },
  {
    "serial": "8440203357"
  },
  {
    "serial": "1347841841"
  },
  {
    "serial": "5922539068"
  },
  {
    "serial": "9490305563"
  },
  {
    "serial": "7919661764"
  },
  {
    "serial": "2561793775"
  },
  {
    "serial": "4104233871"
  },
  {
    "serial": "1731133482"
  },
  {
    "serial": "1149032599"
  },
  {
    "serial": "8114446571"
  },
  {
    "serial": "5908624231"
  },
  {
    "serial": "3322312251"
  },
  {
    "serial": "3887144271"
  },
  {
    "serial": "4187595717"
  },
  {
    "serial": "1500476534"
  },
  {
    "serial": "4152783058"
  },
  {
    "serial": "5334982765"
  },
  {
    "serial": "7304445708"
  },
  {
    "serial": "1390931127"
  },
  {
    "serial": "7796746175"
  },
  {
    "serial": "5737207232"
  },
  {
    "serial": "7993976864"
  },
  {
    "serial": "5933539230"
  },
  {
    "serial": "4610794671"
  },
  {
    "serial": "2211627282"
  },
  {
    "serial": "0975515065"
  },
  {
    "serial": "8890720447"
  },
  {
    "serial": "4383299494"
  },
  {
    "serial": "5382249869"
  },
  {
    "serial": "9114128151"
  },
  {
    "serial": "5552062399"
  },
  {
    "serial": "4526777141"
  },
  {
    "serial": "8343457902"
  },
  {
    "serial": "2207993375"
  },
  {
    "serial": "3758854636"
  },
  {
    "serial": "2232443164"
  },
  {
    "serial": "5838093135"
  },
  {
    "serial": "5662144327"
  },
  {
    "serial": "9209000505"
  },
  {
    "serial": "3366219628"
  },
  {
    "serial": "2783261452"
  },
  {
    "serial": "8157833636"
  },
  {
    "serial": "6092116943"
  },
  {
    "serial": "9162943444"
  },
  {
    "serial": "5184694262"
  },
  {
    "serial": "0502241110"
  },
  {
    "serial": "5361997041"
  },
  {
    "serial": "4458882752"
  },
  {
    "serial": "6155706770"
  },
  {
    "serial": "1948015522"
  },
  {
    "serial": "2427573452"
  },
  {
    "serial": "5309160363"
  },
  {
    "serial": "7959241626"
  },
  {
    "serial": "5913527791"
  },
  {
    "serial": "5547644392"
  },
  {
    "serial": "2654340658"
  },
  {
    "serial": "5154141997"
  },
  {
    "serial": "5350385752"
  },
  {
    "serial": "3632455980"
  },
  {
    "serial": "8903763004"
  },
  {
    "serial": "8129143593"
  },
  {
    "serial": "2175719273"
  },
  {
    "serial": "9189630644"
  },
  {
    "serial": "6464855144"
  },
  {
    "serial": "8465365842"
  },
  {
    "serial": "6468708802"
  },
  {
    "serial": "8800543285"
  },
  {
    "serial": "4136254911"
  },
  {
    "serial": "2862103740"
  },
  {
    "serial": "1497798254"
  },
  {
    "serial": "3392290882"
  },
  {
    "serial": "8534727469"
  },
  {
    "serial": "5057077280"
  },
  {
    "serial": "9716988291"
  },
  {
    "serial": "7257176250"
  },
  {
    "serial": "5467432331"
  },
  {
    "serial": "9966079510"
  },
  {
    "serial": "5985442093"
  },
  {
    "serial": "8916736401"
  },
  {
    "serial": "8331004435"
  },
  {
    "serial": "7762347784"
  },
  {
    "serial": "3990694543"
  },
  {
    "serial": "8253680311"
  },
  {
    "serial": "5967446773"
  },
  {
    "serial": "8809026803"
  },
  {
    "serial": "5961012191"
  },
  {
    "serial": "7130183168"
  },
  {
    "serial": "2406438115"
  },
  {
    "serial": "7843933990"
  },
  {
    "serial": "9601755474"
  },
  {
    "serial": "3771724063"
  },
  {
    "serial": "2224496097"
  },
  {
    "serial": "1466690573"
  },
  {
    "serial": "5174230614"
  },
  {
    "serial": "0750596496"
  },
  {
    "serial": "7040469673"
  },
  {
    "serial": "3472870157"
  },
  {
    "serial": "0619024003"
  },
  {
    "serial": "3837565930"
  },
  {
    "serial": "1534643760"
  },
  {
    "serial": "9270300347"
  },
  {
    "serial": "6825832618"
  },
  {
    "serial": "9795706879"
  },
  {
    "serial": "3379233095"
  },
  {
    "serial": "3807147099"
  },
  {
    "serial": "4833727755"
  },
  {
    "serial": "1903629754"
  },
  {
    "serial": "5007197139"
  },
  {
    "serial": "1094407317"
  },
  {
    "serial": "4457240069"
  },
  {
    "serial": "5770995768"
  },
  {
    "serial": "5179993919"
  },
  {
    "serial": "0602056400"
  },
  {
    "serial": "0928090232"
  },
  {
    "serial": "1226318523"
  },
  {
    "serial": "4227338961"
  },
  {
    "serial": "9251229366"
  },
  {
    "serial": "0580329472"
  },
  {
    "serial": "8805434134"
  },
  {
    "serial": "0825456973"
  },
  {
    "serial": "5756934500"
  },
  {
    "serial": "8601156352"
  },
  {
    "serial": "1591906159"
  },
  {
    "serial": "2788464481"
  },
  {
    "serial": "1931332165"
  },
  {
    "serial": "0827758889"
  },
  {
    "serial": "2587833282"
  },
  {
    "serial": "3466971763"
  },
  {
    "serial": "0961449691"
  },
  {
    "serial": "8978421348"
  },
  {
    "serial": "6316242871"
  },
  {
    "serial": "9388865520"
  },
  {
    "serial": "8277085927"
  },
  {
    "serial": "2103403073"
  },
  {
    "serial": "0400865333"
  },
  {
    "serial": "4648345793"
  },
  {
    "serial": "4947682904"
  },
  {
    "serial": "6198048693"
  },
  {
    "serial": "4851831570"
  },
  {
    "serial": "1156778415"
  },
  {
    "serial": "7500778050"
  },
  {
    "serial": "8990105101"
  },
  {
    "serial": "9793501165"
  },
  {
    "serial": "0518882360"
  },
  {
    "serial": "2634666008"
  },
  {
    "serial": "8128219493"
  },
  {
    "serial": "1643752148"
  },
  {
    "serial": "8458769315"
  },
  {
    "serial": "5634517980"
  },
  {
    "serial": "3757032952"
  },
  {
    "serial": "9212960877"
  },
  {
    "serial": "6982055342"
  },
  {
    "serial": "6555362349"
  },
  {
    "serial": "7496796702"
  },
  {
    "serial": "9806961604"
  },
  {
    "serial": "3673963686"
  },
  {
    "serial": "8956773983"
  },
  {
    "serial": "0275017457"
  },
  {
    "serial": "1160108930"
  },
  {
    "serial": "2614156228"
  },
  {
    "serial": "2153974536"
  },
  {
    "serial": "2161005737"
  },
  {
    "serial": "1068619970"
  },
  {
    "serial": "7573621690"
  },
  {
    "serial": "2882036342"
  },
  {
    "serial": "0988712675"
  },
  {
    "serial": "9559009510"
  },
  {
    "serial": "4139177796"
  },
  {
    "serial": "9656282929"
  },
  {
    "serial": "2073382844"
  },
  {
    "serial": "3994831430"
  },
  {
    "serial": "5987779708"
  },
  {
    "serial": "4642293825"
  },
  {
    "serial": "0134205384"
  },
  {
    "serial": "2945216469"
  },
  {
    "serial": "7206102258"
  },
  {
    "serial": "7800477189"
  },
  {
    "serial": "3331379903"
  },
  {
    "serial": "0923599807"
  },
  {
    "serial": "5911648987"
  },
  {
    "serial": "5733272198"
  },
  {
    "serial": "6548016523"
  },
  {
    "serial": "1114260555"
  },
  {
    "serial": "0337285373"
  },
  {
    "serial": "7894128029"
  },
  {
    "serial": "3325143695"
  },
  {
    "serial": "8856287571"
  },
  {
    "serial": "4304826946"
  },
  {
    "serial": "8502018834"
  },
  {
    "serial": "6203908048"
  },
  {
    "serial": "6329909615"
  },
  {
    "serial": "5471023985"
  },
  {
    "serial": "4739066126"
  },
  {
    "serial": "3342467457"
  },
  {
    "serial": "3423638646"
  },
  {
    "serial": "3563690514"
  },
  {
    "serial": "1966829911"
  },
  {
    "serial": "0684969314"
  },
  {
    "serial": "2832557678"
  },
  {
    "serial": "8996874361"
  },
  {
    "serial": "3727991899"
  },
  {
    "serial": "1725360612"
  },
  {
    "serial": "9984584756"
  },
  {
    "serial": "4056810569"
  },
  {
    "serial": "5659970247"
  },
  {
    "serial": "9497446436"
  },
  {
    "serial": "3038191296"
  },
  {
    "serial": "2872184631"
  },
  {
    "serial": "1799081599"
  },
  {
    "serial": "5607417226"
  },
  {
    "serial": "5780750195"
  },
  {
    "serial": "0040933160"
  },
  {
    "serial": "4443555695"
  },
  {
    "serial": "2833027697"
  },
  {
    "serial": "2154957399"
  },
  {
    "serial": "0398155747"
  },
  {
    "serial": "6337259870"
  },
  {
    "serial": "2861666713"
  },
  {
    "serial": "4335788669"
  },
  {
    "serial": "2607651623"
  },
  {
    "serial": "0844679944"
  },
  {
    "serial": "9114392476"
  },
  {
    "serial": "4562079865"
  },
  {
    "serial": "4634615167"
  },
  {
    "serial": "8242755786"
  },
  {
    "serial": "8089057346"
  },
  {
    "serial": "9486833453"
  },
  {
    "serial": "1076472628"
  },
  {
    "serial": "3428547388"
  },
  {
    "serial": "0136938909"
  },
  {
    "serial": "0382112530"
  },
  {
    "serial": "6368128770"
  },
  {
    "serial": "6906861775"
  },
  {
    "serial": "2995978869"
  },
  {
    "serial": "1747376448"
  },
  {
    "serial": "8380298227"
  },
  {
    "serial": "4047237625"
  },
  {
    "serial": "5674380166"
  },
  {
    "serial": "4484635083"
  },
  {
    "serial": "7643277127"
  },
  {
    "serial": "8466114546"
  },
  {
    "serial": "2843566973"
  },
  {
    "serial": "8097886496"
  },
  {
    "serial": "5803404499"
  },
  {
    "serial": "0375241833"
  },
  {
    "serial": "0192766327"
  },
  {
    "serial": "3758407344"
  },
  {
    "serial": "6487051556"
  },
  {
    "serial": "2757857848"
  },
  {
    "serial": "4945756452"
  },
  {
    "serial": "1010867487"
  },
  {
    "serial": "1304520271"
  },
  {
    "serial": "8568179801"
  },
  {
    "serial": "1288236316"
  },
  {
    "serial": "1681004683"
  },
  {
    "serial": "4175232653"
  },
  {
    "serial": "6702721595"
  },
  {
    "serial": "6951311627"
  },
  {
    "serial": "2607045180"
  },
  {
    "serial": "8135126202"
  },
  {
    "serial": "3657887372"
  },
  {
    "serial": "4875225213"
  },
  {
    "serial": "1415827375"
  },
  {
    "serial": "4765052388"
  },
  {
    "serial": "7927394168"
  },
  {
    "serial": "1333121026"
  },
  {
    "serial": "3220681435"
  },
  {
    "serial": "0949715320"
  },
  {
    "serial": "1417702055"
  },
  {
    "serial": "0659753560"
  },
  {
    "serial": "6059103330"
  },
  {
    "serial": "9565585453"
  },
  {
    "serial": "4485262978"
  },
  {
    "serial": "1707777916"
  },
  {
    "serial": "4454102908"
  },
  {
    "serial": "1180591578"
  },
  {
    "serial": "7605877245"
  },
  {
    "serial": "1040791657"
  },
  {
    "serial": "6555049730"
  },
  {
    "serial": "9029208825"
  },
  {
    "serial": "5744054437"
  },
  {
    "serial": "7882043339"
  },
  {
    "serial": "6557629240"
  },
  {
    "serial": "6395974717"
  },
  {
    "serial": "2855416315"
  },
  {
    "serial": "9503145899"
  },
  {
    "serial": "2837676267"
  },
  {
    "serial": "2045359938"
  },
  {
    "serial": "2394442392"
  },
  {
    "serial": "4077140798"
  },
  {
    "serial": "8254618674"
  },
  {
    "serial": "4989209939"
  },
  {
    "serial": "2268131956"
  },
  {
    "serial": "9187039996"
  },
  {
    "serial": "8563237307"
  },
  {
    "serial": "5214521345"
  },
  {
    "serial": "1389434232"
  },
  {
    "serial": "2786254710"
  },
  {
    "serial": "1673119481"
  },
  {
    "serial": "0438848376"
  },
  {
    "serial": "5370023326"
  },
  {
    "serial": "3141801070"
  },
  {
    "serial": "4228156784"
  },
  {
    "serial": "3096506195"
  },
  {
    "serial": "3258667926"
  },
  {
    "serial": "1007480229"
  },
  {
    "serial": "4595937014"
  },
  {
    "serial": "1312710989"
  },
  {
    "serial": "8880313641"
  },
  {
    "serial": "0718369663"
  },
  {
    "serial": "2599340854"
  },
  {
    "serial": "6766440496"
  },
  {
    "serial": "0994364883"
  },
  {
    "serial": "4298351687"
  },
  {
    "serial": "8483899293"
  },
  {
    "serial": "4973492012"
  },
  {
    "serial": "1792436741"
  },
  {
    "serial": "7104362152"
  },
  {
    "serial": "1256932680"
  },
  {
    "serial": "2672639693"
  },
  {
    "serial": "2024998102"
  },
  {
    "serial": "1849315559"
  },
  {
    "serial": "1958839449"
  },
  {
    "serial": "9973364822"
  },
  {
    "serial": "9191187203"
  },
  {
    "serial": "3256277983"
  },
  {
    "serial": "9909020779"
  },
  {
    "serial": "9026736133"
  },
  {
    "serial": "6707842107"
  },
  {
    "serial": "3740324458"
  },
  {
    "serial": "9346461404"
  },
  {
    "serial": "6908430199"
  },
  {
    "serial": "4156008155"
  },
  {
    "serial": "5150510328"
  },
  {
    "serial": "0198771479"
  },
  {
    "serial": "5598289469"
  },
  {
    "serial": "3959768106"
  },
  {
    "serial": "4388855951"
  },
  {
    "serial": "4440531053"
  },
  {
    "serial": "9531640259"
  },
  {
    "serial": "5407091007"
  },
  {
    "serial": "6742025502"
  },
  {
    "serial": "2429461748"
  },
  {
    "serial": "2683432294"
  },
  {
    "serial": "2070404088"
  },
  {
    "serial": "3314768668"
  },
  {
    "serial": "3870371824"
  },
  {
    "serial": "9759040786"
  },
  {
    "serial": "9013970604"
  },
  {
    "serial": "7382307952"
  },
  {
    "serial": "9893201245"
  },
  {
    "serial": "2077274161"
  },
  {
    "serial": "3619284619"
  },
  {
    "serial": "0662374388"
  },
  {
    "serial": "2327809808"
  },
  {
    "serial": "3685149019"
  },
  {
    "serial": "4921280196"
  },
  {
    "serial": "2501175406"
  },
  {
    "serial": "5752688845"
  },
  {
    "serial": "2671262018"
  },
  {
    "serial": "6127957733"
  },
  {
    "serial": "0464530377"
  },
  {
    "serial": "8907933819"
  },
  {
    "serial": "4738889114"
  },
  {
    "serial": "4134838269"
  },
  {
    "serial": "8529587860"
  },
  {
    "serial": "3252513365"
  },
  {
    "serial": "7302178509"
  },
  {
    "serial": "2699571788"
  },
  {
    "serial": "1951868940"
  },
  {
    "serial": "8889974211"
  },
  {
    "serial": "0578789026"
  },
  {
    "serial": "1363034453"
  },
  {
    "serial": "6730159701"
  },
  {
    "serial": "9830470978"
  },
  {
    "serial": "2415182662"
  },
  {
    "serial": "3314455019"
  },
  {
    "serial": "9903101633"
  },
  {
    "serial": "7698835860"
  },
  {
    "serial": "9823977658"
  },
  {
    "serial": "1740316540"
  },
  {
    "serial": "1110070834"
  },
  {
    "serial": "2844195624"
  },
  {
    "serial": "5633576003"
  },
  {
    "serial": "3528888765"
  },
  {
    "serial": "2737586210"
  },
  {
    "serial": "1487194399"
  },
  {
    "serial": "1769551506"
  },
  {
    "serial": "3659407252"
  },
  {
    "serial": "0348047770"
  },
  {
    "serial": "8314912943"
  },
  {
    "serial": "5677478314"
  },
  {
    "serial": "4703185456"
  },
  {
    "serial": "3081730065"
  },
  {
    "serial": "8069013277"
  },
  {
    "serial": "6787306726"
  },
  {
    "serial": "2642799734"
  },
  {
    "serial": "6983120756"
  },
  {
    "serial": "7920196297"
  },
  {
    "serial": "8462178313"
  },
  {
    "serial": "3976743355"
  },
  {
    "serial": "3565086083"
  },
  {
    "serial": "8903383894"
  },
  {
    "serial": "5592209745"
  },
  {
    "serial": "2970952558"
  },
  {
    "serial": "1646364057"
  },
  {
    "serial": "3798632489"
  },
  {
    "serial": "6711040052"
  },
  {
    "serial": "7169561466"
  },
  {
    "serial": "6334500664"
  },
  {
    "serial": "9998982822"
  },
  {
    "serial": "5800062092"
  },
  {
    "serial": "2158036372"
  },
  {
    "serial": "5289053091"
  },
  {
    "serial": "2910486873"
  },
  {
    "serial": "4240786428"
  },
  {
    "serial": "3730907981"
  },
  {
    "serial": "9461929565"
  },
  {
    "serial": "5449227965"
  },
  {
    "serial": "5855031653"
  },
  {
    "serial": "5325796166"
  },
  {
    "serial": "4470634710"
  },
  {
    "serial": "6265709490"
  },
  {
    "serial": "5606895075"
  },
  {
    "serial": "1800459081"
  },
  {
    "serial": "0734473226"
  },
  {
    "serial": "3691703999"
  },
  {
    "serial": "5826764812"
  },
  {
    "serial": "7576985720"
  },
  {
    "serial": "4156206486"
  },
  {
    "serial": "7317611577"
  },
  {
    "serial": "4306018237"
  },
  {
    "serial": "4245312899"
  },
  {
    "serial": "4566414936"
  },
  {
    "serial": "7700052561"
  },
  {
    "serial": "3054174861"
  },
  {
    "serial": "5616814686"
  },
  {
    "serial": "5907943020"
  },
  {
    "serial": "3182204762"
  },
  {
    "serial": "8943474604"
  },
  {
    "serial": "0214038812"
  },
  {
    "serial": "9474034171"
  },
  {
    "serial": "5792111998"
  },
  {
    "serial": "9248410400"
  },
  {
    "serial": "7556076185"
  },
  {
    "serial": "2844463311"
  },
  {
    "serial": "6392435530"
  },
  {
    "serial": "1983588391"
  },
  {
    "serial": "4610563324"
  },
  {
    "serial": "4405132640"
  },
  {
    "serial": "8509387224"
  },
  {
    "serial": "7366413495"
  },
  {
    "serial": "7950986310"
  },
  {
    "serial": "5123135666"
  },
  {
    "serial": "6011820716"
  },
  {
    "serial": "1745085264"
  },
  {
    "serial": "0142760255"
  },
  {
    "serial": "6757725434"
  },
  {
    "serial": "3891441135"
  },
  {
    "serial": "0053296794"
  },
  {
    "serial": "3959454749"
  },
  {
    "serial": "7336848028"
  },
  {
    "serial": "2269224784"
  },
  {
    "serial": "3086437146"
  },
  {
    "serial": "6279499989"
  },
  {
    "serial": "7227590721"
  },
  {
    "serial": "1673213169"
  },
  {
    "serial": "8138579860"
  },
  {
    "serial": "3176320046"
  },
  {
    "serial": "1589172145"
  },
  {
    "serial": "9673138492"
  },
  {
    "serial": "2141699500"
  },
  {
    "serial": "8828025851"
  },
  {
    "serial": "5851958834"
  },
  {
    "serial": "6921615859"
  },
  {
    "serial": "6410196163"
  },
  {
    "serial": "1810957066"
  },
  {
    "serial": "9848006228"
  },
  {
    "serial": "1397809813"
  },
  {
    "serial": "6691555558"
  },
  {
    "serial": "9055199138"
  },
  {
    "serial": "7853415276"
  },
  {
    "serial": "3774474328"
  },
  {
    "serial": "0515073872"
  },
  {
    "serial": "4350380293"
  },
  {
    "serial": "6600564808"
  },
  {
    "serial": "7277094988"
  },
  {
    "serial": "2251410714"
  },
  {
    "serial": "3490862913"
  },
  {
    "serial": "7300605982"
  },
  {
    "serial": "8178155944"
  },
  {
    "serial": "1367077896"
  },
  {
    "serial": "8011227603"
  },
  {
    "serial": "5656188959"
  },
  {
    "serial": "1158547396"
  },
  {
    "serial": "3442053173"
  },
  {
    "serial": "1278437429"
  },
  {
    "serial": "4013909025"
  },
  {
    "serial": "8881930864"
  },
  {
    "serial": "3044062168"
  },
  {
    "serial": "0082093436"
  },
  {
    "serial": "8513880610"
  },
  {
    "serial": "6667276221"
  },
  {
    "serial": "7810950936"
  },
  {
    "serial": "9311193636"
  },
  {
    "serial": "4252679826"
  },
  {
    "serial": "5516279022"
  },
  {
    "serial": "1764601868"
  },
  {
    "serial": "3064564093"
  },
  {
    "serial": "3027508880"
  },
  {
    "serial": "4241206764"
  },
  {
    "serial": "3514505910"
  },
  {
    "serial": "2122513837"
  },
  {
    "serial": "1537788794"
  },
  {
    "serial": "7951359582"
  },
  {
    "serial": "2577008556"
  },
  {
    "serial": "6698703144"
  },
  {
    "serial": "9590969300"
  },
  {
    "serial": "5319669320"
  },
  {
    "serial": "5983806075"
  },
  {
    "serial": "3993388481"
  },
  {
    "serial": "5297048786"
  },
  {
    "serial": "3126687254"
  },
  {
    "serial": "0081114720"
  },
  {
    "serial": "8512335517"
  },
  {
    "serial": "2508136823"
  },
  {
    "serial": "5829622603"
  },
  {
    "serial": "9912165603"
  },
  {
    "serial": "3215991112"
  },
  {
    "serial": "2313297349"
  },
  {
    "serial": "5428778509"
  },
  {
    "serial": "2283392088"
  },
  {
    "serial": "4847270248"
  },
  {
    "serial": "6207374015"
  },
  {
    "serial": "9161366704"
  },
  {
    "serial": "1411592601"
  },
  {
    "serial": "8024658398"
  },
  {
    "serial": "1841584616"
  },
  {
    "serial": "2284712615"
  },
  {
    "serial": "7703561063"
  },
  {
    "serial": "3667099323"
  },
  {
    "serial": "4092336983"
  },
  {
    "serial": "4946021096"
  },
  {
    "serial": "3722550021"
  },
  {
    "serial": "5487237322"
  },
  {
    "serial": "0346538135"
  },
  {
    "serial": "6524623607"
  },
  {
    "serial": "3364029417"
  },
  {
    "serial": "6556995535"
  },
  {
    "serial": "6917305838"
  },
  {
    "serial": "6254577668"
  },
  {
    "serial": "5277807151"
  },
  {
    "serial": "1601274150"
  },
  {
    "serial": "4836855645"
  },
  {
    "serial": "2900202603"
  },
  {
    "serial": "0013582341"
  },
  {
    "serial": "9129525862"
  },
  {
    "serial": "2787362926"
  },
  {
    "serial": "5900455964"
  },
  {
    "serial": "9262095418"
  },
  {
    "serial": "1406194116"
  },
  {
    "serial": "3847345364"
  },
  {
    "serial": "0235542503"
  },
  {
    "serial": "5361806309"
  },
  {
    "serial": "0440712347"
  },
  {
    "serial": "6683746207"
  },
  {
    "serial": "7971667048"
  },
  {
    "serial": "3756059220"
  },
  {
    "serial": "8882540738"
  },
  {
    "serial": "2341854533"
  },
  {
    "serial": "1713240974"
  },
  {
    "serial": "6300465983"
  },
  {
    "serial": "4177146638"
  },
  {
    "serial": "5064960544"
  },
  {
    "serial": "4014997409"
  },
  {
    "serial": "1976146314"
  },
  {
    "serial": "8227819250"
  },
  {
    "serial": "0103642526"
  },
  {
    "serial": "5876127423"
  },
  {
    "serial": "5607410338"
  },
  {
    "serial": "1789291794"
  },
  {
    "serial": "2724400789"
  },
  {
    "serial": "4133653719"
  },
  {
    "serial": "9180125156"
  },
  {
    "serial": "6393133704"
  },
  {
    "serial": "3001216856"
  },
  {
    "serial": "5405169409"
  },
  {
    "serial": "4909877401"
  },
  {
    "serial": "8336529840"
  },
  {
    "serial": "1774675944"
  },
  {
    "serial": "1665108815"
  },
  {
    "serial": "2826296531"
  },
  {
    "serial": "5364598663"
  },
  {
    "serial": "1004100671"
  },
  {
    "serial": "4133472524"
  },
  {
    "serial": "4236722270"
  },
  {
    "serial": "6411943621"
  },
  {
    "serial": "2836528444"
  },
  {
    "serial": "4096627486"
  },
  {
    "serial": "1661016020"
  },
  {
    "serial": "9305934557"
  },
  {
    "serial": "8303574852"
  },
  {
    "serial": "9134854059"
  },
  {
    "serial": "4098726666"
  },
  {
    "serial": "7959605960"
  },
  {
    "serial": "2492247180"
  },
  {
    "serial": "7498506851"
  },
  {
    "serial": "7050254098"
  },
  {
    "serial": "9844239195"
  },
  {
    "serial": "5708743447"
  },
  {
    "serial": "5674718357"
  },
  {
    "serial": "1024492710"
  },
  {
    "serial": "6038862758"
  },
  {
    "serial": "0735673519"
  },
  {
    "serial": "0667637540"
  },
  {
    "serial": "3467015271"
  },
  {
    "serial": "1185056817"
  },
  {
    "serial": "4749144509"
  }
]
